svncl/__init__.py
svncl/changelog.py
svncl/resources/README.md
svncl/resources/README.rst
svncl/resources/requirements.txt
svncl/resources/scripts/svncl
svncl-0.2.4.data/scripts/svncl
svncl-0.2.4.dist-info/DESCRIPTION.rst
svncl-0.2.4.dist-info/METADATA
svncl-0.2.4.dist-info/metadata.json
svncl-0.2.4.dist-info/RECORD
svncl-0.2.4.dist-info/top_level.txt
svncl-0.2.4.dist-info/WHEEL
