Metadata-Version: 2.0
Name: svncl
Version: 0.2.4
Summary: Generate changelog text for Subversion commits since the last tag.
Home-page: https://github.com/dsoprea/SvnCl
Author: Dustin Oprea
Author-email: myselfasunder@gmail.com
License: GPL 2
Keywords: subversion svn changelog
Platform: UNKNOWN
Requires-Dist: python-dateutil (==2.2)
Requires-Dist: six (==1.7.2)
Requires-Dist: svn
